MANIFEST.in
README.MD
setup.py
hello_world/__init__.py
hello_world/greeting.py
hello_world_from_ivan.egg-info/PKG-INFO
hello_world_from_ivan.egg-info/SOURCES.txt
hello_world_from_ivan.egg-info/dependency_links.txt
hello_world_from_ivan.egg-info/top_level.txt