Metadata-Version: 2.1
Name: hello-world-from-ivan
Version: 0.0.3.3
Summary: Shows how to use setup.py
Home-page: https://www.domain.com
Author: Ivan Pavlov
License: GPLv3
Keywords: tutorial
Platform: UNKNOWN
Classifier: Development Status :: 4 - Beta
Classifier: Intended Audience :: Developers
Classifier: Programming Language :: Python
Classifier: Programming Language :: Python :: 3.5
Classifier: Programming Language :: Python :: 3.6
